setup.py
ezprogbar/__init__.py
ezprogbar/ezprogbar.py
ezprogbar/test.py
ezprogbar.egg-info/PKG-INFO
ezprogbar.egg-info/SOURCES.txt
ezprogbar.egg-info/dependency_links.txt
ezprogbar.egg-info/not-zip-safe
ezprogbar.egg-info/top_level.txt