Metadata-Version: 1.0
Name: ezprogbar
Version: 1.21
Summary: simple textual progress bar
Home-page: http://github.com/samyzaf/ezprogbar
Author: Samy Zafrany
Author-email: admin@samyzaf.com
License: MIT
Platform: UNKNOWN
